README.md
pytest_cli2_ansible.py
setup.py
pytest_cli2_ansible.egg-info/PKG-INFO
pytest_cli2_ansible.egg-info/SOURCES.txt
pytest_cli2_ansible.egg-info/dependency_links.txt
pytest_cli2_ansible.egg-info/entry_points.txt
pytest_cli2_ansible.egg-info/top_level.txt